[{"Price": 2243300, "Amount": 100, "Side": false}, {"Price": 2243200, "Amount": 100, "Side": false}, {"Price": 2243300, "Amount": 100, "Side": false}, {"Price": 2243500, "Amount": 100, "Side": false}, {"Price": 2243300, "Amount": 100, "Side": false}, {"Price": 2243600, "Amount": 20, "Side": false}, {"Price": 2243600, "Amount": 20, "Side": false}, {"Price": 2243600, "Amount": 20, "Side": false}, {"Price": 2242300, "Amount": 75, "Side": true}, {"Price": 2242500, "Amount": 100, "Side": false}, {"Price": 2242000, "Amount": 200, "Side": true}, {"Price": 2242500, "Amount": 100, "Side": false}, {"Price": 2242000, "Amount": 200, "Side": true}, {"Price": 2242000, "Amount": 200, "Side": true}, {"Price": 2242000, "Amount": 200, "Side": true}, {"Price": 2242000, "Amount": 200, "Side": true}, {"Price": 2242000, "Amount": 200, "Side": true}, {"Price": 2242000, "Amount": 200, "Side": true}, {"Price": 2242000, "Amount": 200, "Side": true}, {"Price": 2242000, "Amount": 200, "Side": true}, {"Price": 2242500, "Amount": 13, "Side": false}, {"Price": 2242000, "Amount": 200, "Side": true}, {"Price": 2242000, "Amount": 200, "Side": true}, {"Price": 2242000, "Amount": 200, "Side": true}, {"Price": 2242000, "Amount": 200, "Side": true}, {"Price": 2242000, "Amount": 200, "Side": true}, {"Price": 2242000, "Amount": 200, "Side": true}, {"Price": 2242000, "Amount": 200, "Side": true}, {"Price": 2242000, "Amount": 200, "Side": true}, {"Price": 2242000, "Amount": 200, "Side": true}, {"Price": 2242100, "Amount": 400, "Side": false}, {"Price": 2243500, "Amount": 20, "Side": false}, {"Price": 2243500, "Amount": 20, "Side": false}, {"Price": 2243400, "Amount": 100, "Side": false}, {"Price": 2243000, "Amount": 10, "Side": false}, {"Price": 2243100, "Amount": 10, "Side": false}, {"Price": 2243100, "Amount": 10, "Side": false}, {"Price": 2243100, "Amount": 10, "Side": false}, {"Price": 2243000, "Amount": 10, "Side": false}, {"Price": 2243000, "Amount": 10, "Side": false}, {"Price": 2243000, "Amount": 10, "Side": false}, {"Price": 2243100, "Amount": 10, "Side": false}, {"Price": 2242000, "Amount": 200, "Side": true}, {"Price": 2242000, "Amount": 200, "Side": true}, {"Price": 2243000, "Amount": 100, "Side": false}, {"Price": 2243000, "Amount": 100, "Side": false}, {"Price": 2242500, "Amount": 2, "Side": false}, {"Price": 2242000, "Amount": 79, "Side": true}, {"Price": 2241100, "Amount": 20, "Side": true}, {"Price": 2242400, "Amount": 100, "Side": false}, {"Price": 2242000, "Amount": 400, "Side": false}, {"Price": 2241700, "Amount": 100, "Side": false}, {"Price": 2242000, "Amount": 20, "Side": false}, {"Price": 2241900, "Amount": 17, "Side": false}, {"Price": 2239900, "Amount": 17, "Side": true}, {"Price": 2241500, "Amount": 100, "Side": false}, {"Price": 2241800, "Amount": 13, "Side": false}, {"Price": 2241400, "Amount": 100, "Side": false}, {"Price": 2240200, "Amount": 100, "Side": true}, {"Price": 2241200, "Amount": 100, "Side": false}, {"Price": 2241100, "Amount": 100, "Side": false}, {"Price": 2241300, "Amount": 100, "Side": false}, {"Price": 2239900, "Amount": 20, "Side": true}, {"Price": 2240100, "Amount": 20, "Side": true}, {"Price": 2241800, "Amount": 13, "Side": false}, {"Price": 2241000, "Amount": 100, "Side": false}, {"Price": 2239900, "Amount": 17, "Side": true}, {"Price": 2239900, "Amount": 20, "Side": true}, {"Price": 2240000, "Amount": 17, "Side": true}, {"Price": 2240000, "Amount": 6, "Side": true}, {"Price": 2240000, "Amount": 20, "Side": true}, {"Price": 2241700, "Amount": 100, "Side": false}, {"Price": 2240800, "Amount": 100, "Side": true}, {"Price": 2241500, "Amount": 100, "Side": false}, {"Price": 2241800, "Amount": 10, "Side": false}, {"Price": 2241800, "Amount": 10, "Side": false}, {"Price": 2242500, "Amount": 17, "Side": false}, {"Price": 2242500, "Amount": 20, "Side": false}, {"Price": 2242400, "Amount": 100, "Side": false}, {"Price": 2242300, "Amount": 100, "Side": false}, {"Price": 2241800, "Amount": 100, "Side": false}, {"Price": 2241400, "Amount": 400, "Side": false}, {"Price": 2241400, "Amount": 100, "Side": false}, {"Price": 2241400, "Amount": 200, "Side": true}, {"Price": 2242400, "Amount": 100, "Side": false}, {"Price": 2240800, "Amount": 20, "Side": true}, {"Price": 2240900, "Amount": 20, "Side": true}, {"Price": 2242500, "Amount": 13, "Side": false}, {"Price": 2242500, "Amount": 100, "Side": false}, {"Price": 2242400, "Amount": 100, "Side": false}, {"Price": 2242300, "Amount": 100, "Side": false}, {"Price": 2242300, "Amount": 20, "Side": false}, {"Price": 2242200, "Amount": 100, "Side": false}, {"Price": 2242200, "Amount": 100, "Side": false}, {"Price": 2242200, "Amount": 100, "Side": false}, {"Price": 2240800, "Amount": 20, "Side": true}, {"Price": 2240800, "Amount": 20, "Side": true}, {"Price": 2240800, "Amount": 20, "Side": true}, {"Price": 2242200, "Amount": 100, "Side": false}, {"Price": 2242200, "Amount": 13, "Side": false}, {"Price": 2242100, "Amount": 100, "Side": false}, {"Price": 2242100, "Amount": 100, "Side": false}, {"Price": 2241900, "Amount": 100, "Side": false}, {"Price": 2242200, "Amount": 100, "Side": false}, {"Price": 2242200, "Amount": 19, "Side": false}, {"Price": 2241800, "Amount": 400, "Side": false}, {"Price": 2241700, "Amount": 100, "Side": false}, {"Price": 2241600, "Amount": 100, "Side": false}, {"Price": 2241600, "Amount": 100, "Side": false}, {"Price": 2241600, "Amount": 19, "Side": false}, {"Price": 2241500, "Amount": 100, "Side": false}, {"Price": 2241400, "Amount": 100, "Side": false}, {"Price": 2241400, "Amount": 8, "Side": false}, {"Price": 2241300, "Amount": 100, "Side": false}, {"Price": 2241200, "Amount": 100, "Side": false}, {"Price": 2241200, "Amount": 100, "Side": false}, {"Price": 2240300, "Amount": 10, "Side": true}, {"Price": 2240200, "Amount": 10, "Side": true}, {"Price": 2240200, "Amount": 10, "Side": true}, {"Price": 2240200, "Amount": 10, "Side": true}, {"Price": 2240100, "Amount": 10, "Side": true}, {"Price": 2240100, "Amount": 10, "Side": true}, {"Price": 2240200, "Amount": 10, "Side": true}, {"Price": 2240200, "Amount": 10, "Side": true}, {"Price": 2240900, "Amount": 400, "Side": false}, {"Price": 2240900, "Amount": 100, "Side": false}, {"Price": 2240800, "Amount": 100, "Side": false}, {"Price": 2240800, "Amount": 100, "Side": false}, {"Price": 2239600, "Amount": 6, "Side": true}, {"Price": 2239600, "Amount": 16, "Side": true}, {"Price": 2241600, "Amount": 19, "Side": false}, {"Price": 2239600, "Amount": 19, "Side": true}, {"Price": 2239600, "Amount": 10, "Side": true}, {"Price": 2240800, "Amount": 100, "Side": false}, {"Price": 2239700, "Amount": 10, "Side": true}, {"Price": 2239800, "Amount": 10, "Side": true}, {"Price": 2239900, "Amount": 10, "Side": true}, {"Price": 2239900, "Amount": 100, "Side": true}, {"Price": 2240000, "Amount": 10, "Side": true}, {"Price": 2240000, "Amount": 100, "Side": true}, {"Price": 2240100, "Amount": 10, "Side": true}, {"Price": 2240100, "Amount": 10, "Side": true}, {"Price": 2240200, "Amount": 10, "Side": true}, {"Price": 2240200, "Amount": 10, "Side": true}, {"Price": 2241800, "Amount": 100, "Side": false}, {"Price": 2241700, "Amount": 100, "Side": false}, {"Price": 2240100, "Amount": 10, "Side": true}, {"Price": 2240100, "Amount": 6, "Side": true}, {"Price": 2240200, "Amount": 10, "Side": true}, {"Price": 2241700, "Amount": 19, "Side": false}, {"Price": 2240100, "Amount": 10, "Side": true}, {"Price": 2241700, "Amount": 8, "Side": false}, {"Price": 2241600, "Amount": 16, "Side": false}, {"Price": 2241600, "Amount": 19, "Side": false}, {"Price": 2239900, "Amount": 10, "Side": true}, {"Price": 2239800, "Amount": 10, "Side": true}, {"Price": 2241500, "Amount": 19, "Side": false}, {"Price": 2239700, "Amount": 10, "Side": true}, {"Price": 2241500, "Amount": 8, "Side": false}, {"Price": 2240700, "Amount": 100, "Side": false}, {"Price": 2239500, "Amount": 10, "Side": true}, {"Price": 2239500, "Amount": 10, "Side": true}, {"Price": 2239500, "Amount": 10, "Side": true}, {"Price": 2239500, "Amount": 10, "Side": true}, {"Price": 2239400, "Amount": 10, "Side": true}, {"Price": 2239500, "Amount": 10, "Side": true}, {"Price": 2239100, "Amount": 6, "Side": true}, {"Price": 2239700, "Amount": 100, "Side": true}, {"Price": 2240500, "Amount": 100, "Side": false}, {"Price": 2240500, "Amount": 100, "Side": false}, {"Price": 2240500, "Amount": 100, "Side": false}, {"Price": 2240500, "Amount": 100, "Side": false}, {"Price": 2240500, "Amount": 100, "Side": false}, {"Price": 2239800, "Amount": 100, "Side": true}, {"Price": 2240300, "Amount": 200, "Side": false}, {"Price": 2240300, "Amount": 200, "Side": false}, {"Price": 2240200, "Amount": 100, "Side": false}, {"Price": 2239800, "Amount": 100, "Side": true}, {"Price": 2240200, "Amount": 100, "Side": false}, {"Price": 2240100, "Amount": 100, "Side": false}, {"Price": 2240000, "Amount": 100, "Side": false}, {"Price": 2240000, "Amount": 100, "Side": false}, {"Price": 2239900, "Amount": 100, "Side": false}, {"Price": 2239900, "Amount": 100, "Side": false}, {"Price": 2239900, "Amount": 100, "Side": false}, {"Price": 2239900, "Amount": 100, "Side": false}, {"Price": 2239800, "Amount": 100, "Side": true}, {"Price": 2239900, "Amount": 100, "Side": false}, {"Price": 2239800, "Amount": 100, "Side": true}, {"Price": 2239100, "Amount": 6, "Side": true}, {"Price": 2239100, "Amount": 19, "Side": true}, {"Price": 2240200, "Amount": 100, "Side": false}, {"Price": 2239900, "Amount": 100, "Side": true}, {"Price": 2241300, "Amount": 19, "Side": false}, {"Price": 2241300, "Amount": 8, "Side": false}, {"Price": 2240000, "Amount": 100, "Side": true}, {"Price": 2240000, "Amount": 100, "Side": true}, {"Price": 2240000, "Amount": 100, "Side": true}, {"Price": 2241500, "Amount": 10, "Side": false}, {"Price": 2241800, "Amount": 400, "Side": false}, {"Price": 2240000, "Amount": 6, "Side": true}, {"Price": 2240100, "Amount": 1, "Side": true}, {"Price": 2241800, "Amount": 19, "Side": false}, {"Price": 2241500, "Amount": 100, "Side": false}, {"Price": 2240200, "Amount": 100, "Side": true}, {"Price": 2241300, "Amount": 100, "Side": false}, {"Price": 2241500, "Amount": 8, "Side": false}, {"Price": 2241500, "Amount": 19, "Side": false}, {"Price": 2241300, "Amount": 200, "Side": false}, {"Price": 2240200, "Amount": 100, "Side": true}, {"Price": 2240200, "Amount": 100, "Side": true}, {"Price": 2241200, "Amount": 100, "Side": false}, {"Price": 2241200, "Amount": 100, "Side": true}, {"Price": 2241800, "Amount": 50, "Side": false}, {"Price": 2240400, "Amount": 100, "Side": true}, {"Price": 2240400, "Amount": 100, "Side": true}, {"Price": 2240400, "Amount": 100, "Side": true}, {"Price": 2241100, "Amount": 100, "Side": false}, {"Price": 2241100, "Amount": 50, "Side": false}, {"Price": 2240600, "Amount": 200, "Side": true}, {"Price": 2240600, "Amount": 200, "Side": true}, {"Price": 2241100, "Amount": 100, "Side": false}, {"Price": 2240700, "Amount": 100, "Side": true}, {"Price": 2241100, "Amount": 100, "Side": false}, {"Price": 2241000, "Amount": 100, "Side": false}, {"Price": 2240700, "Amount": 100, "Side": true}, {"Price": 2240800, "Amount": 100, "Side": true}, {"Price": 2240900, "Amount": 100, "Side": true}, {"Price": 2240900, "Amount": 100, "Side": true}, {"Price": 2241000, "Amount": 100, "Side": true}, {"Price": 2241000, "Amount": 100, "Side": true}, {"Price": 2241000, "Amount": 100, "Side": true}, {"Price": 2241000, "Amount": 100, "Side": true}, {"Price": 2241000, "Amount": 100, "Side": true}, {"Price": 2241100, "Amount": 100, "Side": false}, {"Price": 2241100, "Amount": 100, "Side": false}, {"Price": 2241100, "Amount": 100, "Side": false}, {"Price": 2240000, "Amount": 6, "Side": true}, {"Price": 2241800, "Amount": 19, "Side": false}, {"Price": 2241400, "Amount": 16, "Side": false}, {"Price": 2241400, "Amount": 19, "Side": false}, {"Price": 2241200, "Amount": 100, "Side": false}, {"Price": 2240900, "Amount": 16, "Side": false}, {"Price": 2240800, "Amount": 1, "Side": false}, {"Price": 2240800, "Amount": 2, "Side": false}, {"Price": 2240900, "Amount": 2, "Side": false}, {"Price": 2239100, "Amount": 19, "Side": true}, {"Price": 2241100, "Amount": 2, "Side": false}, {"Price": 2239300, "Amount": 16, "Side": true}, {"Price": 2239300, "Amount": 6, "Side": true}, {"Price": 2239300, "Amount": 19, "Side": true}, {"Price": 2240000, "Amount": 1, "Side": true}, {"Price": 2241300, "Amount": 2, "Side": false}, {"Price": 2241000, "Amount": 100, "Side": false}, {"Price": 2240900, "Amount": 2, "Side": false}, {"Price": 2241300, "Amount": 2, "Side": false}, {"Price": 2240800, "Amount": 100, "Side": false}, {"Price": 2240700, "Amount": 2, "Side": false}, {"Price": 2240700, "Amount": 100, "Side": false}, {"Price": 2240000, "Amount": 1, "Side": true}, {"Price": 2240700, "Amount": 8, "Side": false}, {"Price": 2240600, "Amount": 100, "Side": false}, {"Price": 2240500, "Amount": 2, "Side": false}, {"Price": 2239900, "Amount": 100, "Side": true}, {"Price": 2240500, "Amount": 100, "Side": false}, {"Price": 2240100, "Amount": 1, "Side": true}, {"Price": 2240500, "Amount": 100, "Side": false}, {"Price": 2240500, "Amount": 100, "Side": false}, {"Price": 2240000, "Amount": 100, "Side": true}, {"Price": 2240500, "Amount": 200, "Side": false}, {"Price": 2240500, "Amount": 200, "Side": false}, {"Price": 2240400, "Amount": 100, "Side": false}, {"Price": 2240300, "Amount": 2, "Side": false}, {"Price": 2240300, "Amount": 100, "Side": false}, {"Price": 2240000, "Amount": 100, "Side": true}, {"Price": 2240200, "Amount": 100, "Side": false}, {"Price": 2240100, "Amount": 2, "Side": false}, {"Price": 2240100, "Amount": 100, "Side": false}, {"Price": 2240100, "Amount": 100, "Side": false}, {"Price": 2240000, "Amount": 100, "Side": true}, {"Price": 2240000, "Amount": 100, "Side": true}, {"Price": 2240100, "Amount": 100, "Side": false}, {"Price": 2240100, "Amount": 100, "Side": false}, {"Price": 2240000, "Amount": 100, "Side": true}, {"Price": 2240100, "Amount": 100, "Side": false}, {"Price": 2240000, "Amount": 100, "Side": true}, {"Price": 2240000, "Amount": 19, "Side": true}, {"Price": 2240000, "Amount": 100, "Side": true}, {"Price": 2240000, "Amount": 100, "Side": true}, {"Price": 2241700, "Amount": 8, "Side": false}, {"Price": 2241500, "Amount": 100, "Side": false}, {"Price": 2240100, "Amount": 100, "Side": true}, {"Price": 2240100, "Amount": 100, "Side": true}, {"Price": 2240100, "Amount": 100, "Side": true}, {"Price": 2240100, "Amount": 100, "Side": true}, {"Price": 2240100, "Amount": 300, "Side": true}, {"Price": 2240200, "Amount": 2, "Side": true}, {"Price": 2241000, "Amount": 100, "Side": false}, {"Price": 2240500, "Amount": 200, "Side": true}, {"Price": 2240500, "Amount": 200, "Side": true}, {"Price": 2240600, "Amount": 100, "Side": true}, {"Price": 2240600, "Amount": 100, "Side": true}, {"Price": 2241000, "Amount": 100, "Side": false}, {"Price": 2241000, "Amount": 100, "Side": false}, {"Price": 2240700, "Amount": 100, "Side": true}, {"Price": 2240800, "Amount": 100, "Side": true}, {"Price": 2240800, "Amount": 100, "Side": true}, {"Price": 2240900, "Amount": 100, "Side": true}, {"Price": 2240900, "Amount": 100, "Side": true}, {"Price": 2240900, "Amount": 100, "Side": true}, {"Price": 2240900, "Amount": 100, "Side": true}, {"Price": 2240900, "Amount": 100, "Side": true}, {"Price": 2240400, "Amount": 200, "Side": true}, {"Price": 2240400, "Amount": 300, "Side": true}, {"Price": 2241500, "Amount": 100, "Side": false}, {"Price": 2241500, "Amount": 100, "Side": false}, {"Price": 2240200, "Amount": 300, "Side": true}, {"Price": 2240300, "Amount": 100, "Side": true}, {"Price": 2240700, "Amount": 300, "Side": true}, {"Price": 2240500, "Amount": 300, "Side": true}, {"Price": 2240300, "Amount": 300, "Side": true}, {"Price": 2241500, "Amount": 100, "Side": false}, {"Price": 2241500, "Amount": 100, "Side": false}, {"Price": 2241500, "Amount": 100, "Side": false}, {"Price": 2241500, "Amount": 100, "Side": false}, {"Price": 2241500, "Amount": 100, "Side": false}, {"Price": 2241500, "Amount": 100, "Side": false}, {"Price": 2241500, "Amount": 100, "Side": false}, {"Price": 2241500, "Amount": 100, "Side": false}, {"Price": 2241400, "Amount": 2, "Side": true}, {"Price": 2240800, "Amount": 200, "Side": true}, {"Price": 2240600, "Amount": 200, "Side": true}, {"Price": 2240300, "Amount": 300, "Side": true}, {"Price": 2241800, "Amount": 10, "Side": false}, {"Price": 2241700, "Amount": 100, "Side": false}, {"Price": 2240500, "Amount": 100, "Side": true}, {"Price": 2240600, "Amount": 100, "Side": true}, {"Price": 2240600, "Amount": 100, "Side": true}, {"Price": 2241300, "Amount": 100, "Side": false}, {"Price": 2240800, "Amount": 200, "Side": true}, {"Price": 2240800, "Amount": 100, "Side": true}, {"Price": 2240800, "Amount": 200, "Side": true}, {"Price": 2240900, "Amount": 100, "Side": true}, {"Price": 2240900, "Amount": 100, "Side": true}, {"Price": 2240900, "Amount": 100, "Side": true}, {"Price": 2241000, "Amount": 100, "Side": true}, {"Price": 2241000, "Amount": 100, "Side": true}, {"Price": 2241100, "Amount": 100, "Side": true}, {"Price": 2241100, "Amount": 100, "Side": true}, {"Price": 2241200, "Amount": 100, "Side": true}, {"Price": 2241200, "Amount": 100, "Side": true}, {"Price": 2241200, "Amount": 100, "Side": true}, {"Price": 2241200, "Amount": 100, "Side": true}, {"Price": 2241300, "Amount": 100, "Side": false}, {"Price": 2241300, "Amount": 100, "Side": false}, {"Price": 2241200, "Amount": 100, "Side": true}, {"Price": 2241000, "Amount": 100, "Side": true}, {"Price": 2240900, "Amount": 100, "Side": true}, {"Price": 2240900, "Amount": 100, "Side": true}, {"Price": 2241300, "Amount": 100, "Side": true}, {"Price": 2240500, "Amount": 15, "Side": true}, {"Price": 2240500, "Amount": 17, "Side": true}, {"Price": 2240800, "Amount": 100, "Side": true}, {"Price": 2240800, "Amount": 15, "Side": true}, {"Price": 2240800, "Amount": 17, "Side": true}, {"Price": 2242800, "Amount": 15, "Side": false}, {"Price": 2240800, "Amount": 6, "Side": true}, {"Price": 2242800, "Amount": 17, "Side": false}, {"Price": 2242700, "Amount": 12, "Side": false}, {"Price": 2241200, "Amount": 100, "Side": true}, {"Price": 2242800, "Amount": 17, "Side": false}, {"Price": 2242700, "Amount": 15, "Side": false}, {"Price": 2240700, "Amount": 17, "Side": true}, {"Price": 2242800, "Amount": 15, "Side": false}, {"Price": 2242700, "Amount": 17, "Side": false}, {"Price": 2242100, "Amount": 200, "Side": false}, {"Price": 2242100, "Amount": 17, "Side": false}, {"Price": 2241700, "Amount": 100, "Side": false}, {"Price": 2241500, "Amount": 100, "Side": false}, {"Price": 2240100, "Amount": 17, "Side": true}, {"Price": 2240100, "Amount": 6, "Side": true}, {"Price": 2241500, "Amount": 100, "Side": false}, {"Price": 2240300, "Amount": 100, "Side": true}, {"Price": 2240300, "Amount": 100, "Side": true}, {"Price": 2240300, "Amount": 17, "Side": true}, {"Price": 2240400, "Amount": 100, "Side": true}, {"Price": 2240400, "Amount": 17, "Side": true}, {"Price": 2240400, "Amount": 100, "Side": true}, {"Price": 2240500, "Amount": 100, "Side": true}, {"Price": 2240500, "Amount": 17, "Side": true}, {"Price": 2240500, "Amount": 15, "Side": true}, {"Price": 2240800, "Amount": 15, "Side": true}, {"Price": 2240800, "Amount": 6, "Side": true}, {"Price": 2242800, "Amount": 15, "Side": false}, {"Price": 2240800, "Amount": 17, "Side": true}, {"Price": 2241600, "Amount": 100, "Side": true}, {"Price": 2241800, "Amount": 100, "Side": true}, {"Price": 2243200, "Amount": 400, "Side": false}, {"Price": 2241800, "Amount": 100, "Side": true}, {"Price": 2241900, "Amount": 100, "Side": true}, {"Price": 2243500, "Amount": 17, "Side": false}, {"Price": 2243500, "Amount": 12, "Side": false}, {"Price": 2243000, "Amount": 100, "Side": false}, {"Price": 2241800, "Amount": 100, "Side": true}, {"Price": 2241800, "Amount": 17, "Side": true}, {"Price": 2241800, "Amount": 17, "Side": true}, {"Price": 2243100, "Amount": 100, "Side": false}, {"Price": 2242200, "Amount": 10, "Side": true}, {"Price": 2242100, "Amount": 10, "Side": true}, {"Price": 2242100, "Amount": 10, "Side": true}, {"Price": 2242900, "Amount": 100, "Side": false}, {"Price": 2242100, "Amount": 100, "Side": true}, {"Price": 2242500, "Amount": 3, "Side": true}, {"Price": 2243500, "Amount": 17, "Side": false}, {"Price": 2242200, "Amount": 100, "Side": true}, {"Price": 2242200, "Amount": 100, "Side": true}, {"Price": 2242500, "Amount": 100, "Side": true}, {"Price": 2243500, "Amount": 100, "Side": false}, {"Price": 2243500, "Amount": 17, "Side": false}, {"Price": 2243000, "Amount": 100, "Side": true}, {"Price": 2244000, "Amount": 100, "Side": false}, {"Price": 2244000, "Amount": 17, "Side": false}, {"Price": 2243100, "Amount": 100, "Side": true}, {"Price": 2242500, "Amount": 17, "Side": true}, {"Price": 2242500, "Amount": 100, "Side": true}, {"Price": 2242500, "Amount": 17, "Side": true}, {"Price": 2244000, "Amount": 10, "Side": false}, {"Price": 2243900, "Amount": 10, "Side": false}, {"Price": 2244000, "Amount": 10, "Side": false}, {"Price": 2243900, "Amount": 10, "Side": false}, {"Price": 2243900, "Amount": 100, "Side": false}, {"Price": 2243800, "Amount": 10, "Side": false}, {"Price": 2243700, "Amount": 10, "Side": false}, {"Price": 2243700, "Amount": 10, "Side": false}, {"Price": 2243800, "Amount": 10, "Side": false}, {"Price": 2243800, "Amount": 10, "Side": false}, {"Price": 2243800, "Amount": 10, "Side": false}, {"Price": 2243700, "Amount": 10, "Side": false}, {"Price": 2243800, "Amount": 10, "Side": false}, {"Price": 2242600, "Amount": 100, "Side": true}, {"Price": 2243900, "Amount": 17, "Side": false}, {"Price": 2242500, "Amount": 17, "Side": true}, {"Price": 2243900, "Amount": 9, "Side": false}, {"Price": 2243900, "Amount": 17, "Side": false}, {"Price": 2243700, "Amount": 100, "Side": false}, {"Price": 2242500, "Amount": 19, "Side": true}, {"Price": 2242600, "Amount": 2, "Side": true}, {"Price": 2242600, "Amount": 2, "Side": true}, {"Price": 2243700, "Amount": 100, "Side": false}, {"Price": 2242800, "Amount": 2, "Side": true}, {"Price": 2242800, "Amount": 2, "Side": true}, {"Price": 2243100, "Amount": 2, "Side": true}, {"Price": 2243300, "Amount": 2, "Side": true}, {"Price": 2243800, "Amount": 100, "Side": false}, {"Price": 2243700, "Amount": 100, "Side": false}, {"Price": 2243600, "Amount": 100, "Side": false}, {"Price": 2243500, "Amount": 100, "Side": false}, {"Price": 2242400, "Amount": 19, "Side": true}, {"Price": 2243500, "Amount": 100, "Side": false}, {"Price": 2243500, "Amount": 100, "Side": false}, {"Price": 2243300, "Amount": 100, "Side": false}, {"Price": 2243300, "Amount": 100, "Side": false}, {"Price": 2242100, "Amount": 100, "Side": true}, {"Price": 2242100, "Amount": 10, "Side": true}, {"Price": 2242200, "Amount": 10, "Side": true}, {"Price": 2242100, "Amount": 10, "Side": true}, {"Price": 2242200, "Amount": 10, "Side": true}, {"Price": 2242100, "Amount": 10, "Side": true}, {"Price": 2242100, "Amount": 10, "Side": true}, {"Price": 2242900, "Amount": 100, "Side": false}, {"Price": 2242900, "Amount": 100, "Side": false}, {"Price": 2242100, "Amount": 10, "Side": true}, {"Price": 2242900, "Amount": 100, "Side": false}, {"Price": 2242100, "Amount": 200, "Side": true}, {"Price": 2242800, "Amount": 100, "Side": false}, {"Price": 2242800, "Amount": 100, "Side": false}, {"Price": 2242800, "Amount": 100, "Side": false}, {"Price": 2242500, "Amount": 5, "Side": false}, {"Price": 2242500, "Amount": 100, "Side": false}, {"Price": 2242400, "Amount": 100, "Side": false}, {"Price": 2241700, "Amount": 100, "Side": true}, {"Price": 2242200, "Amount": 200, "Side": false}, {"Price": 2242200, "Amount": 100, "Side": false}, {"Price": 2242200, "Amount": 200, "Side": false}, {"Price": 2242100, "Amount": 100, "Side": false}, {"Price": 2242100, "Amount": 100, "Side": false}, {"Price": 2242100, "Amount": 100, "Side": false}, {"Price": 2242000, "Amount": 100, "Side": false}, {"Price": 2242000, "Amount": 100, "Side": false}, {"Price": 2241700, "Amount": 100, "Side": true}, {"Price": 2241900, "Amount": 100, "Side": false}, {"Price": 2241700, "Amount": 100, "Side": true}, {"Price": 2241700, "Amount": 100, "Side": true}, {"Price": 2241900, "Amount": 100, "Side": false}, {"Price": 2241900, "Amount": 100, "Side": false}, {"Price": 2241900, "Amount": 100, "Side": false}, {"Price": 2241800, "Amount": 100, "Side": false}, {"Price": 2241800, "Amount": 100, "Side": false}, {"Price": 2241800, "Amount": 100, "Side": false}, {"Price": 2241800, "Amount": 100, "Side": false}, {"Price": 2241900, "Amount": 100, "Side": true}, {"Price": 2242000, "Amount": 100, "Side": false}, {"Price": 2241800, "Amount": 100, "Side": false}, {"Price": 2241400, "Amount": 6, "Side": true}, {"Price": 2243300, "Amount": 100, "Side": false}, {"Price": 2241500, "Amount": 19, "Side": true}, {"Price": 2241500, "Amount": 6, "Side": true}, {"Price": 2243100, "Amount": 100, "Side": false}, {"Price": 2243000, "Amount": 100, "Side": false}, {"Price": 2241500, "Amount": 100, "Side": true}, {"Price": 2243000, "Amount": 100, "Side": false}, {"Price": 2242800, "Amount": 100, "Side": false}, {"Price": 2241600, "Amount": 19, "Side": true}, {"Price": 2241600, "Amount": 100, "Side": true}, {"Price": 2241600, "Amount": 6, "Side": true}, {"Price": 2242600, "Amount": 100, "Side": false}, {"Price": 2241600, "Amount": 6, "Side": true}, {"Price": 2241900, "Amount": 100, "Side": true}, {"Price": 2241900, "Amount": 100, "Side": true}, {"Price": 2241900, "Amount": 19, "Side": true}, {"Price": 2241900, "Amount": 6, "Side": true}, {"Price": 2243400, "Amount": 19, "Side": false}, {"Price": 2243400, "Amount": 100, "Side": false}, {"Price": 2243400, "Amount": 19, "Side": false}, {"Price": 2243400, "Amount": 19, "Side": false}, {"Price": 2243400, "Amount": 19, "Side": false}, {"Price": 2243200, "Amount": 100, "Side": false}, {"Price": 2243000, "Amount": 100, "Side": false}, {"Price": 2242700, "Amount": 100, "Side": false}, {"Price": 2242700, "Amount": 100, "Side": false}, {"Price": 2242200, "Amount": 100, "Side": true}, {"Price": 2242700, "Amount": 200, "Side": false}, {"Price": 2242700, "Amount": 200, "Side": false}, {"Price": 2242600, "Amount": 100, "Side": false}, {"Price": 2242600, "Amount": 100, "Side": false}, {"Price": 2242500, "Amount": 100, "Side": false}, {"Price": 2242200, "Amount": 100, "Side": true}, {"Price": 2242400, "Amount": 100, "Side": false}, {"Price": 2242200, "Amount": 100, "Side": true}, {"Price": 2242200, "Amount": 100, "Side": true}, {"Price": 2242400, "Amount": 100, "Side": false}, {"Price": 2242300, "Amount": 100, "Side": false}, {"Price": 2242300, "Amount": 100, "Side": false}, {"Price": 2242300, "Amount": 100, "Side": false}, {"Price": 2242300, "Amount": 100, "Side": false}, {"Price": 2242200, "Amount": 100, "Side": true}, {"Price": 2242200, "Amount": 100, "Side": true}, {"Price": 2242200, "Amount": 100, "Side": true}, {"Price": 2242200, "Amount": 100, "Side": true}, {"Price": 2242200, "Amount": 100, "Side": true}, {"Price": 2242300, "Amount": 100, "Side": false}, {"Price": 2242700, "Amount": 100, "Side": false}, {"Price": 2241600, "Amount": 19, "Side": true}, {"Price": 2241600, "Amount": 6, "Side": true}, {"Price": 2242100, "Amount": 300, "Side": true}, {"Price": 2242100, "Amount": 100, "Side": true}, {"Price": 2242300, "Amount": 100, "Side": true}, {"Price": 2242400, "Amount": 100, "Side": true}, {"Price": 2242400, "Amount": 100, "Side": true}, {"Price": 2242500, "Amount": 100, "Side": true}, {"Price": 2242400, "Amount": 100, "Side": true}, {"Price": 2243500, "Amount": 100, "Side": false}, {"Price": 2243500, "Amount": 19, "Side": false}, {"Price": 2243500, "Amount": 4, "Side": false}, {"Price": 2241600, "Amount": 19, "Side": true}, {"Price": 2241600, "Amount": 6, "Side": true}, {"Price": 2241600, "Amount": 19, "Side": true}, {"Price": 2243500, "Amount": 19, "Side": false}, {"Price": 2241600, "Amount": 100, "Side": true}, {"Price": 2241600, "Amount": 16, "Side": true}, {"Price": 2243500, "Amount": 19, "Side": false}, {"Price": 2242300, "Amount": 100, "Side": true}, {"Price": 2241700, "Amount": 100, "Side": true}, {"Price": 2241700, "Amount": 100, "Side": true}, {"Price": 2242300, "Amount": 100, "Side": true}, {"Price": 2243500, "Amount": 19, "Side": false}, {"Price": 2243500, "Amount": 19, "Side": false}, {"Price": 2241700, "Amount": 100, "Side": true}, {"Price": 2241700, "Amount": 6, "Side": true}, {"Price": 2241700, "Amount": 100, "Side": true}, {"Price": 2242300, "Amount": 100, "Side": true}, {"Price": 2242300, "Amount": 200, "Side": true}, {"Price": 2242300, "Amount": 100, "Side": true}, {"Price": 2242300, "Amount": 19, "Side": true}, {"Price": 2242400, "Amount": 100, "Side": true}, {"Price": 2242500, "Amount": 100, "Side": true}, {"Price": 2242500, "Amount": 100, "Side": true}, {"Price": 2242600, "Amount": 200, "Side": true}, {"Price": 2242600, "Amount": 2, "Side": true}, {"Price": 2242600, "Amount": 5, "Side": true}, {"Price": 2243500, "Amount": 100, "Side": false}, {"Price": 2242800, "Amount": 100, "Side": true}, {"Price": 2242800, "Amount": 100, "Side": true}, {"Price": 2242800, "Amount": 100, "Side": true}, {"Price": 2242800, "Amount": 100, "Side": true}, {"Price": 2243500, "Amount": 5, "Side": true}, {"Price": 2243200, "Amount": 100, "Side": true}, {"Price": 2243200, "Amount": 100, "Side": true}, {"Price": 2243200, "Amount": 19, "Side": true}, {"Price": 2244800, "Amount": 19, "Side": false}, {"Price": 2243000, "Amount": 19, "Side": true}, {"Price": 2243200, "Amount": 1, "Side": true}, {"Price": 2244800, "Amount": 19, "Side": false}, {"Price": 2244500, "Amount": 100, "Side": false}, {"Price": 2244000, "Amount": 2, "Side": true}, {"Price": 2243500, "Amount": 2, "Side": true}, {"Price": 2243500, "Amount": 1, "Side": true}, {"Price": 2243300, "Amount": 100, "Side": false}, {"Price": 2242500, "Amount": 19, "Side": true}, {"Price": 2242600, "Amount": 19, "Side": true}, {"Price": 2243900, "Amount": 100, "Side": false}, {"Price": 2243800, "Amount": 100, "Side": false}, {"Price": 2243700, "Amount": 100, "Side": false}, {"Price": 2243700, "Amount": 10, "Side": false}, {"Price": 2243700, "Amount": 19, "Side": false}, {"Price": 2242100, "Amount": 19, "Side": true}, {"Price": 2243700, "Amount": 100, "Side": false}, {"Price": 2243500, "Amount": 100, "Side": false}, {"Price": 2243400, "Amount": 100, "Side": false}, {"Price": 2243400, "Amount": 100, "Side": false}, {"Price": 2243400, "Amount": 100, "Side": false}, {"Price": 2242500, "Amount": 100, "Side": true}, {"Price": 2242500, "Amount": 100, "Side": true}, {"Price": 2243000, "Amount": 200, "Side": false}, {"Price": 2243000, "Amount": 200, "Side": false}, {"Price": 2242500, "Amount": 2, "Side": true}, {"Price": 2242900, "Amount": 100, "Side": false}, {"Price": 2242900, "Amount": 100, "Side": false}, {"Price": 2242800, "Amount": 100, "Side": false}, {"Price": 2242700, "Amount": 100, "Side": false}, {"Price": 2242700, "Amount": 100, "Side": false}, {"Price": 2242600, "Amount": 100, "Side": false}, {"Price": 2242700, "Amount": 100, "Side": false}, {"Price": 2242600, "Amount": 100, "Side": false}, {"Price": 2242600, "Amount": 100, "Side": false}, {"Price": 2242600, "Amount": 100, "Side": false}, {"Price": 2242700, "Amount": 1, "Side": true}, {"Price": 2242600, "Amount": 99, "Side": false}, {"Price": 2242600, "Amount": 100, "Side": false}, {"Price": 2244200, "Amount": 16, "Side": false}, {"Price": 2243500, "Amount": 100, "Side": false}, {"Price": 2243500, "Amount": 100, "Side": false}, {"Price": 2243400, "Amount": 100, "Side": false}, {"Price": 2243400, "Amount": 100, "Side": false}, {"Price": 2242800, "Amount": 100, "Side": true}, {"Price": 2243300, "Amount": 200, "Side": false}, {"Price": 2243300, "Amount": 200, "Side": false}, {"Price": 2243200, "Amount": 100, "Side": false}, {"Price": 2243200, "Amount": 100, "Side": false}, {"Price": 2243100, "Amount": 100, "Side": false}, {"Price": 2243100, "Amount": 100, "Side": false}, {"Price": 2243000, "Amount": 100, "Side": false}, {"Price": 2243000, "Amount": 100, "Side": false}, {"Price": 2242900, "Amount": 100, "Side": false}, {"Price": 2242800, "Amount": 100, "Side": true}, {"Price": 2242800, "Amount": 100, "Side": true}, {"Price": 2242800, "Amount": 100, "Side": true}, {"Price": 2242800, "Amount": 100, "Side": true}, {"Price": 2242900, "Amount": 100, "Side": false}, {"Price": 2242800, "Amount": 100, "Side": true}, {"Price": 2242800, "Amount": 100, "Side": true}, {"Price": 2242800, "Amount": 60, "Side": true}, {"Price": 2242900, "Amount": 100, "Side": false}, {"Price": 2242900, "Amount": 100, "Side": false}, {"Price": 2242900, "Amount": 100, "Side": false}, {"Price": 2242000, "Amount": 19, "Side": true}, {"Price": 2242500, "Amount": 19, "Side": true}, {"Price": 2242500, "Amount": 100, "Side": true}, {"Price": 2242500, "Amount": 100, "Side": true}, {"Price": 2242500, "Amount": 4, "Side": true}, {"Price": 2242700, "Amount": 100, "Side": true}, {"Price": 2242700, "Amount": 100, "Side": true}, {"Price": 2242700, "Amount": 4, "Side": true}, {"Price": 2242700, "Amount": 100, "Side": true}, {"Price": 2242700, "Amount": 100, "Side": true}, {"Price": 2242700, "Amount": 100, "Side": true}, {"Price": 2243800, "Amount": 100, "Side": false}, {"Price": 2243500, "Amount": 100, "Side": false}, {"Price": 2243000, "Amount": 200, "Side": true}, {"Price": 2243000, "Amount": 4, "Side": true}, {"Price": 2243000, "Amount": 200, "Side": true}, {"Price": 2243100, "Amount": 100, "Side": true}, {"Price": 2243100, "Amount": 4, "Side": true}, {"Price": 2243100, "Amount": 100, "Side": true}, {"Price": 2243200, "Amount": 100, "Side": true}, {"Price": 2243200, "Amount": 4, "Side": true}, {"Price": 2243300, "Amount": 100, "Side": true}, {"Price": 2243300, "Amount": 4, "Side": true}, {"Price": 2243300, "Amount": 100, "Side": true}, {"Price": 2243400, "Amount": 100, "Side": true}, {"Price": 2243400, "Amount": 4, "Side": true}, {"Price": 2243400, "Amount": 100, "Side": true}, {"Price": 2243400, "Amount": 100, "Side": true}, {"Price": 2243400, "Amount": 100, "Side": true}, {"Price": 2242800, "Amount": 10, "Side": true}, {"Price": 2242800, "Amount": 100, "Side": true}, {"Price": 2242800, "Amount": 10, "Side": true}, {"Price": 2242200, "Amount": 19, "Side": true}, {"Price": 2244200, "Amount": 19, "Side": false}, {"Price": 2242300, "Amount": 2, "Side": true}, {"Price": 2242300, "Amount": 100, "Side": true}, {"Price": 2242300, "Amount": 19, "Side": true}, {"Price": 2242500, "Amount": 100, "Side": true}, {"Price": 2242500, "Amount": 100, "Side": true}, {"Price": 2244200, "Amount": 100, "Side": false}, {"Price": 2242500, "Amount": 100, "Side": true}, {"Price": 2242700, "Amount": 100, "Side": true}, {"Price": 2242700, "Amount": 100, "Side": true}, {"Price": 2242700, "Amount": 19, "Side": true}, {"Price": 2242700, "Amount": 100, "Side": true}, {"Price": 2242700, "Amount": 100, "Side": true}, {"Price": 2242700, "Amount": 6, "Side": true}, {"Price": 2244800, "Amount": 4, "Side": false}, {"Price": 2244800, "Amount": 100, "Side": false}, {"Price": 2244800, "Amount": 19, "Side": false}, {"Price": 2244800, "Amount": 12, "Side": false}, {"Price": 2244700, "Amount": 100, "Side": false}, {"Price": 2244700, "Amount": 16, "Side": false}, {"Price": 2244600, "Amount": 16, "Side": false}, {"Price": 2244600, "Amount": 19, "Side": false}, {"Price": 2244600, "Amount": 4, "Side": false}, {"Price": 2242700, "Amount": 19, "Side": true}, {"Price": 2243100, "Amount": 100, "Side": false}, {"Price": 2242700, "Amount": 100, "Side": true}, {"Price": 2242700, "Amount": 100, "Side": true}, {"Price": 2242800, "Amount": 100, "Side": true}, {"Price": 2242900, "Amount": 100, "Side": true}, {"Price": 2242900, "Amount": 100, "Side": true}, {"Price": 2243000, "Amount": 100, "Side": true}, {"Price": 2243100, "Amount": 100, "Side": false}, {"Price": 2243100, "Amount": 100, "Side": false}, {"Price": 2243000, "Amount": 100, "Side": true}, {"Price": 2243000, "Amount": 100, "Side": true}, {"Price": 2243000, "Amount": 100, "Side": true}, {"Price": 2243000, "Amount": 100, "Side": true}, {"Price": 2242500, "Amount": 19, "Side": true}, {"Price": 2244600, "Amount": 100, "Side": false}, {"Price": 2243700, "Amount": 100, "Side": false}, {"Price": 2242700, "Amount": 100, "Side": true}, {"Price": 2242700, "Amount": 100, "Side": true}, {"Price": 2242800, "Amount": 2, "Side": true}, {"Price": 2242800, "Amount": 100, "Side": true}, {"Price": 2242700, "Amount": 100, "Side": true}, {"Price": 2243000, "Amount": 2, "Side": true}, {"Price": 2243000, "Amount": 100, "Side": true}, {"Price": 2242300, "Amount": 6, "Side": true}, {"Price": 2244500, "Amount": 4, "Side": false}, {"Price": 2244400, "Amount": 16, "Side": false}, {"Price": 2242300, "Amount": 19, "Side": true}, {"Price": 2242300, "Amount": 16, "Side": true}, {"Price": 2242400, "Amount": 19, "Side": true}, {"Price": 2242400, "Amount": 6, "Side": true}, {"Price": 2244500, "Amount": 100, "Side": false}, {"Price": 2244400, "Amount": 100, "Side": false}, {"Price": 2244400, "Amount": 19, "Side": false}, {"Price": 2244400, "Amount": 4, "Side": false}, {"Price": 2243000, "Amount": 2, "Side": true}, {"Price": 2244500, "Amount": 100, "Side": false}, {"Price": 2244000, "Amount": 10, "Side": false}, {"Price": 2244200, "Amount": 10, "Side": false}, {"Price": 2244100, "Amount": 10, "Side": false}, {"Price": 2244000, "Amount": 10, "Side": false}, {"Price": 2244100, "Amount": 10, "Side": false}, {"Price": 2243700, "Amount": 100, "Side": false}, {"Price": 2243000, "Amount": 1, "Side": true}, {"Price": 2242100, "Amount": 21, "Side": true}, {"Price": 2243200, "Amount": 100, "Side": true}, {"Price": 2244800, "Amount": 21, "Side": false}, {"Price": 2244700, "Amount": 100, "Side": false}, {"Price": 2244700, "Amount": 100, "Side": false}, {"Price": 2244700, "Amount": 100, "Side": false}, {"Price": 2244600, "Amount": 100, "Side": false}, {"Price": 2244700, "Amount": 100, "Side": false}, {"Price": 2244600, "Amount": 100, "Side": false}, {"Price": 2244700, "Amount": 100, "Side": false}, {"Price": 2244700, "Amount": 21, "Side": false}, {"Price": 2244600, "Amount": 21, "Side": false}, {"Price": 2244600, "Amount": 100, "Side": false}, {"Price": 2243000, "Amount": 2, "Side": true}, {"Price": 2244700, "Amount": 100, "Side": false}, {"Price": 2243700, "Amount": 100, "Side": false}, {"Price": 2243200, "Amount": 100, "Side": false}, {"Price": 2243000, "Amount": 2, "Side": true}, {"Price": 2243200, "Amount": 100, "Side": false}, {"Price": 2243000, "Amount": 100, "Side": true}, {"Price": 2243400, "Amount": 2, "Side": false}, {"Price": 2243000, "Amount": 2, "Side": true}, {"Price": 2243400, "Amount": 2, "Side": true}, {"Price": 2243600, "Amount": 100, "Side": false}, {"Price": 2243700, "Amount": 100, "Side": false}, {"Price": 2243300, "Amount": 100, "Side": true}, {"Price": 2243300, "Amount": 2, "Side": true}, {"Price": 2243400, "Amount": 2, "Side": true}, {"Price": 2243000, "Amount": 10, "Side": true}, {"Price": 2243000, "Amount": 10, "Side": true}, {"Price": 2243600, "Amount": 10, "Side": false}, {"Price": 2243700, "Amount": 10, "Side": false}, {"Price": 2243600, "Amount": 10, "Side": false}, {"Price": 2243700, "Amount": 10, "Side": false}, {"Price": 2243600, "Amount": 10, "Side": false}, {"Price": 2243500, "Amount": 10, "Side": false}, {"Price": 2243600, "Amount": 10, "Side": false}, {"Price": 2243500, "Amount": 10, "Side": false}, {"Price": 2243300, "Amount": 10, "Side": false}, {"Price": 2242600, "Amount": 100, "Side": true}, {"Price": 2243700, "Amount": 12, "Side": false}, {"Price": 2243700, "Amount": 4, "Side": false}, {"Price": 2243700, "Amount": 20, "Side": false}, {"Price": 2243600, "Amount": 20, "Side": false}, {"Price": 2243600, "Amount": 3, "Side": false}, {"Price": 2243600, "Amount": 12, "Side": false}, {"Price": 2242600, "Amount": 100, "Side": true}, {"Price": 2243300, "Amount": 100, "Side": true}, {"Price": 2243400, "Amount": 1, "Side": true}, {"Price": 2243500, "Amount": 100, "Side": false}, {"Price": 2243200, "Amount": 100, "Side": false}, {"Price": 2243200, "Amount": 166, "Side": false}, {"Price": 2243200, "Amount": 100, "Side": false}, {"Price": 2243200, "Amount": 20, "Side": false}, {"Price": 2241000, "Amount": 6, "Side": true}, {"Price": 2241000, "Amount": 15, "Side": true}, {"Price": 2243100, "Amount": 20, "Side": false}, {"Price": 2243100, "Amount": 4, "Side": false}, {"Price": 2241500, "Amount": 100, "Side": true}, {"Price": 2241500, "Amount": 100, "Side": true}, {"Price": 2243100, "Amount": 12, "Side": false}, {"Price": 2242600, "Amount": 100, "Side": false}, {"Price": 2241300, "Amount": 20, "Side": true}, {"Price": 2241300, "Amount": 100, "Side": true}, {"Price": 2241300, "Amount": 15, "Side": true}, {"Price": 2241500, "Amount": 15, "Side": true}, {"Price": 2241500, "Amount": 20, "Side": true}, {"Price": 2243000, "Amount": 100, "Side": false}, {"Price": 2243000, "Amount": 2, "Side": false}, {"Price": 2243000, "Amount": 10, "Side": false}, {"Price": 2243000, "Amount": 20, "Side": false}, {"Price": 2241100, "Amount": 20, "Side": true}, {"Price": 2241100, "Amount": 15, "Side": true}, {"Price": 2241700, "Amount": 10, "Side": true}, {"Price": 2241600, "Amount": 10, "Side": true}, {"Price": 2241500, "Amount": 10, "Side": true}, {"Price": 2241600, "Amount": 10, "Side": true}, {"Price": 2241600, "Amount": 10, "Side": true}, {"Price": 2241600, "Amount": 10, "Side": true}, {"Price": 2241600, "Amount": 10, "Side": true}, {"Price": 2241500, "Amount": 10, "Side": true}, {"Price": 2241600, "Amount": 10, "Side": true}, {"Price": 2241700, "Amount": 10, "Side": true}, {"Price": 2243000, "Amount": 10, "Side": false}, {"Price": 2241700, "Amount": 20, "Side": true}, {"Price": 2241800, "Amount": 10, "Side": true}, {"Price": 2241700, "Amount": 10, "Side": true}, {"Price": 2241800, "Amount": 10, "Side": true}, {"Price": 2241700, "Amount": 10, "Side": true}, {"Price": 2241700, "Amount": 10, "Side": true}, {"Price": 2241800, "Amount": 10, "Side": true}, {"Price": 2241900, "Amount": 10, "Side": true}, {"Price": 2241800, "Amount": 10, "Side": true}, {"Price": 2241700, "Amount": 10, "Side": true}, {"Price": 2241600, "Amount": 10, "Side": true}, {"Price": 2241700, "Amount": 10, "Side": true}, {"Price": 2241600, "Amount": 10, "Side": true}, {"Price": 2243000, "Amount": 10, "Side": false}, {"Price": 2243000, "Amount": 20, "Side": false}, {"Price": 2242900, "Amount": 15, "Side": false}, {"Price": 2242300, "Amount": 100, "Side": false}, {"Price": 2240800, "Amount": 20, "Side": true}, {"Price": 2240900, "Amount": 15, "Side": true}, {"Price": 2240900, "Amount": 20, "Side": true}, {"Price": 2242700, "Amount": 10, "Side": false}, {"Price": 2240900, "Amount": 6, "Side": true}, {"Price": 2241500, "Amount": 20, "Side": true}, {"Price": 2243100, "Amount": 20, "Side": false}, {"Price": 2242900, "Amount": 15, "Side": false}, {"Price": 2241200, "Amount": 20, "Side": true}, {"Price": 2241500, "Amount": 20, "Side": true}, {"Price": 2242800, "Amount": 100, "Side": false}, {"Price": 2241600, "Amount": 100, "Side": true}, {"Price": 2241700, "Amount": 10, "Side": true}, {"Price": 2241600, "Amount": 10, "Side": true}, {"Price": 2241700, "Amount": 10, "Side": true}, {"Price": 2241600, "Amount": 10, "Side": true}, {"Price": 2241700, "Amount": 10, "Side": true}, {"Price": 2241600, "Amount": 10, "Side": true}, {"Price": 2241600, "Amount": 10, "Side": true}, {"Price": 2241700, "Amount": 10, "Side": true}, {"Price": 2241800, "Amount": 10, "Side": true}, {"Price": 2241700, "Amount": 10, "Side": true}, {"Price": 2242700, "Amount": 100, "Side": false}, {"Price": 2241800, "Amount": 100, "Side": true}, {"Price": 2241800, "Amount": 100, "Side": true}, {"Price": 2243000, "Amount": 100, "Side": false}, {"Price": 2241900, "Amount": 100, "Side": true}, {"Price": 2241900, "Amount": 100, "Side": true}, {"Price": 2242900, "Amount": 100, "Side": false}, {"Price": 2242000, "Amount": 100, "Side": true}, {"Price": 2242000, "Amount": 100, "Side": true}, {"Price": 2242100, "Amount": 100, "Side": true}, {"Price": 2243200, "Amount": 100, "Side": false}, {"Price": 2242100, "Amount": 100, "Side": true}, {"Price": 2242100, "Amount": 100, "Side": true}, {"Price": 2243200, "Amount": 96, "Side": false}, {"Price": 2243200, "Amount": 4, "Side": true}, {"Price": 2242200, "Amount": 100, "Side": true}, {"Price": 2242200, "Amount": 100, "Side": true}, {"Price": 2242200, "Amount": 100, "Side": true}, {"Price": 2243400, "Amount": 100, "Side": false}, {"Price": 2242400, "Amount": 100, "Side": true}, {"Price": 2242200, "Amount": 100, "Side": true}, {"Price": 2242400, "Amount": 100, "Side": true}, {"Price": 2242600, "Amount": 100, "Side": true}, {"Price": 2242900, "Amount": 100, "Side": true}, {"Price": 2242400, "Amount": 100, "Side": true}, {"Price": 2242900, "Amount": 100, "Side": true}, {"Price": 2242900, "Amount": 100, "Side": true}, {"Price": 2243700, "Amount": 100, "Side": false}, {"Price": 2243700, "Amount": 11, "Side": false}, {"Price": 2242900, "Amount": 100, "Side": true}, {"Price": 2243700, "Amount": 100, "Side": false}, {"Price": 2243700, "Amount": 100, "Side": false}, {"Price": 2243700, "Amount": 100, "Side": false}, {"Price": 2243700, "Amount": 100, "Side": false}, {"Price": 2243700, "Amount": 100, "Side": false}, {"Price": 2243700, "Amount": 100, "Side": false}, {"Price": 2243000, "Amount": 100, "Side": true}, {"Price": 2243700, "Amount": 100, "Side": false}, {"Price": 2243000, "Amount": 100, "Side": true}, {"Price": 2243000, "Amount": 100, "Side": true}, {"Price": 2243700, "Amount": 100, "Side": false}, {"Price": 2243700, "Amount": 100, "Side": true}, {"Price": 2243700, "Amount": 100, "Side": true}, {"Price": 2243900, "Amount": 4, "Side": true}, {"Price": 2243700, "Amount": 15, "Side": true}, {"Price": 2244800, "Amount": 8, "Side": false}, {"Price": 2244800, "Amount": 15, "Side": false}, {"Price": 2243700, "Amount": 100, "Side": true}, {"Price": 2243700, "Amount": 100, "Side": true}, {"Price": 2243700, "Amount": 100, "Side": true}, {"Price": 2243800, "Amount": 100, "Side": true}, {"Price": 2243800, "Amount": 100, "Side": true}, {"Price": 2243800, "Amount": 100, "Side": true}, {"Price": 2243800, "Amount": 100, "Side": true}, {"Price": 2243900, "Amount": 100, "Side": true}, {"Price": 2243900, "Amount": 100, "Side": true}, {"Price": 2243900, "Amount": 100, "Side": true}, {"Price": 2243900, "Amount": 100, "Side": true}, {"Price": 2243900, "Amount": 100, "Side": true}, {"Price": 2245000, "Amount": 100, "Side": false}, {"Price": 2244200, "Amount": 100, "Side": true}, {"Price": 2244300, "Amount": 100, "Side": true}, {"Price": 2244800, "Amount": 100, "Side": true}, {"Price": 2245000, "Amount": 100, "Side": false}, {"Price": 2245000, "Amount": 100, "Side": false}, {"Price": 2245000, "Amount": 100, "Side": false}, {"Price": 2245000, "Amount": 100, "Side": false}, {"Price": 2244800, "Amount": 98, "Side": true}, {"Price": 2246000, "Amount": 100, "Side": false}, {"Price": 2245900, "Amount": 100, "Side": false}, {"Price": 2245900, "Amount": 100, "Side": false}, {"Price": 2244800, "Amount": 100, "Side": true}, {"Price": 2244800, "Amount": 98, "Side": true}, {"Price": 2245200, "Amount": 98, "Side": true}, {"Price": 2245900, "Amount": 100, "Side": false}, {"Price": 2245000, "Amount": 98, "Side": true}, {"Price": 2244800, "Amount": 98, "Side": true}, {"Price": 2245300, "Amount": 98, "Side": true}, {"Price": 2246000, "Amount": 100, "Side": false}, {"Price": 2245100, "Amount": 98, "Side": true}, {"Price": 2244900, "Amount": 98, "Side": true}, {"Price": 2245000, "Amount": 98, "Side": true}, {"Price": 2245000, "Amount": 100, "Side": true}, {"Price": 2245500, "Amount": 98, "Side": true}, {"Price": 2245700, "Amount": 98, "Side": true}, {"Price": 2245600, "Amount": 98, "Side": true}, {"Price": 2245700, "Amount": 98, "Side": true}, {"Price": 2245400, "Amount": 98, "Side": true}, {"Price": 2245500, "Amount": 100, "Side": true}, {"Price": 2245600, "Amount": 98, "Side": true}, {"Price": 2245600, "Amount": 100, "Side": true}, {"Price": 2246100, "Amount": 98, "Side": true}, {"Price": 2246300, "Amount": 2100, "Side": true}, {"Price": 2246500, "Amount": 98, "Side": true}, {"Price": 2246600, "Amount": 98, "Side": true}, {"Price": 2246900, "Amount": 50, "Side": false}, {"Price": 2246800, "Amount": 100, "Side": false}, {"Price": 2246800, "Amount": 50, "Side": false}, {"Price": 2247300, "Amount": 100, "Side": false}, {"Price": 2247500, "Amount": 100, "Side": false}, {"Price": 2247500, "Amount": 13, "Side": false}, {"Price": 2247600, "Amount": 100, "Side": false}, {"Price": 2247600, "Amount": 13, "Side": false}, {"Price": 2247500, "Amount": 100, "Side": false}, {"Price": 2247700, "Amount": 13, "Side": false}, {"Price": 2248200, "Amount": 8, "Side": false}, {"Price": 2248200, "Amount": 4, "Side": false}, {"Price": 2248200, "Amount": 15, "Side": false}, {"Price": 2248200, "Amount": 13, "Side": false}, {"Price": 2246300, "Amount": 100, "Side": true}, {"Price": 2246300, "Amount": 16, "Side": true}, {"Price": 2246400, "Amount": 100, "Side": true}]